__init__.py
cppchips.py
version.py
cppchips-0.0.1.dist-info/LICENSE.md
cppchips-0.0.1.dist-info/METADATA
cppchips-0.0.1.dist-info/WHEEL
cppchips-0.0.1.dist-info/top_level.txt
cppchips-0.0.1.dist-info/RECORD
