Metadata-Version: 2.1
Name: cppchips
Version: 0.0.1
Summary: Fast C++ Code Generation
Author-email: Leonov Arthur <depish.eskry@yandex.ru>
Project-URL: Homepage, https://github.com/eSkry/cppchips
Project-URL: Bug Tracker, https://github.com/eSkry/cppchips/issues
Classifier: Programming Language :: Python :: 3
Classifier: License :: OSI Approved :: MIT License
Classifier: Operating System :: OS Independent
Requires-Python: >=3.7
License-File: LICENSE.md
